jinjafy/__init__.py
jinjafy/__main__.py
jinjafy/filters.py
jinjafy_automatist-1.0.1.dist-info/LICENSE
jinjafy_automatist-1.0.1.dist-info/METADATA
jinjafy_automatist-1.0.1.dist-info/WHEEL
jinjafy_automatist-1.0.1.dist-info/entry_points.txt
jinjafy_automatist-1.0.1.dist-info/top_level.txt
jinjafy_automatist-1.0.1.dist-info/RECORD
