Metadata-Version: 2.1
Name: jinjafy-automatist
Version: 1.0.1
Summary: Tiny CLI wrapper for jinja2 templates
Home-page: https://gitlab.com/activearchives/jinjafy
Author: Michael Murtaugh
Author-email: mm@automatist.org
License: UNKNOWN
Project-URL: Bug Tracker, https://gitlab.com/activearchives/jinjafy/-/issues
Platform: UNKNOWN
Classifier: Programming Language :: Python :: 3
Classifier: License :: OSI Approved :: MIT License
Classifier: Operating System :: OS Independent
Requires-Python: >=3.6
License-File: LICENSE
Requires-Dist: setuptools
Requires-Dist: jinja2
